lseg_analytics/__init__.py
lseg_analytics-3.0.0b1.dist-info/licenses/LICENSE
lseg_analytics-3.0.0b1.dist-info/METADATA
lseg_analytics-3.0.0b1.dist-info/WHEEL
lseg_analytics-3.0.0b1.dist-info/top_level.txt
lseg_analytics-3.0.0b1.dist-info/RECORD
