Metadata-Version: 2.4
Name: lseg-analytics
Version: 3.0.0b1
Summary: DEPRECATED - This package is no longer maintained. Use lseg-analytics-pricing instead.
Author-email: analyticssdk <analyticssdk@lseg.com>
Maintainer-email: analyticssdk <analyticssdk@lseg.com>
Requires-Python: >=3.8
License-File: LICENSE
Dynamic: license-file
Dynamic: requires-python
